Cutter/Cutter.py
Cutter/__init__.py
Cutter/abbr/ca.list
Cutter/abbr/common.list
Cutter/abbr/de.list
Cutter/abbr/en.list
Cutter/abbr/es.list
Cutter/abbr/fr.list
Cutter/abbr/it.list
Cutter/abbr/nl.list
Cutter/abbr/pt.list
Cutter/abbr/rm.list
Cutter/abbr/ro.list
Cutter/abbr/sv.list
Cutter/init/ca.list
Cutter/init/de.list
Cutter/init/en.list
Cutter/init/es.list
Cutter/init/fr.list
Cutter/init/it.list
Cutter/init/nl.list
Cutter/init/pt.list
Cutter/init/rm.list
Cutter/init/ro.list
Cutter/init/sv.list
Cutter/rule/basic.yaml
Cutter/rule/ca.yaml
Cutter/rule/common.yaml
Cutter/rule/de.yaml
Cutter/rule/en.yaml
Cutter/rule/es.yaml
Cutter/rule/fr.yaml
Cutter/rule/it.yaml
Cutter/rule/nl.yaml
Cutter/rule/pt.yaml
Cutter/rule/rm.yaml
Cutter/rule/ro.yaml
Cutter/rule/sv.yaml
cutter-ng/Cutter.py
cutter-ng/__init__.py
cutter_ng-2.5.dist-info/LICENSE
cutter_ng-2.5.dist-info/METADATA
cutter_ng-2.5.dist-info/WHEEL
cutter_ng-2.5.dist-info/top_level.txt
cutter_ng-2.5.dist-info/RECORD
